setup.py
rockwell/__init__.py
rockwell/rockwell.py
rockwell.egg-info/PKG-INFO
rockwell.egg-info/SOURCES.txt
rockwell.egg-info/dependency_links.txt
rockwell.egg-info/requires.txt
rockwell.egg-info/top_level.txt