Metadata-Version: 1.1
Name: rockwell
Version: 0.0.2
Summary: Watching since 1984
Home-page: https://github.com/danwagnerco/rockwell
Author: Dan Wagner
Author-email: danwagnerco@gmail.com
License: UNKNOWN
Keywords: rockwell
Platform: UNKNOWN
Classifier: Development Status :: 3 - Alpha
Classifier: Environment :: Console
Classifier: Intended Audience :: Developers
Classifier: Operating System :: OS Independent
Classifier: Programming Language :: Python
